matplotsoccer/__init__.py
matplotsoccer/fns.py
matplotsoccer-0.0.4.dist-info/LICENSE.txt
matplotsoccer-0.0.4.dist-info/METADATA
matplotsoccer-0.0.4.dist-info/WHEEL
matplotsoccer-0.0.4.dist-info/top_level.txt
matplotsoccer-0.0.4.dist-info/RECORD
