Metadata-Version: 2.1
Name: matplotsoccer
Version: 0.0.4
Summary: Library for visualizing soccer event stream data
Home-page: http://github.com/tomdecroos/matplotsoccer
Author: Tom Decroos
Author-email: tom.decroos.be@gmail.com
License: MIT
Platform: UNKNOWN
Classifier: Programming Language :: Python :: 3
Classifier: License :: OSI Approved :: MIT License
Classifier: Operating System :: OS Independent
